flight_profiler/__init__.py
flight_profiler/banner.desc
flight_profiler/client.py
flight_profiler/code_inject.py
flight_profiler/common/__init__.py
flight_profiler/common/aop_decorator.py
flight_profiler/common/bytecode_transformer.py
flight_profiler/common/code_wrapper_entity.py
flight_profiler/common/dumps.py
flight_profiler/common/enter_exit_command.py
flight_profiler/common/expression_resolver.py
flight_profiler/common/expression_result.py
flight_profiler/common/global_store.py
flight_profiler/common/system_logger.py
flight_profiler/communication/__init__.py
flight_profiler/communication/base.py
flight_profiler/communication/flight_client.py
flight_profiler/communication/flight_server.py
flight_profiler/ext/gilstat_C.pyi
flight_profiler/ext/stack_C.pyi
flight_profiler/ext/trace_profile_C.pyi
flight_profiler/help_descriptions.py
flight_profiler/plugins/__init__.py
flight_profiler/plugins/cli_plugin.py
flight_profiler/plugins/cls/__init__.py
flight_profiler/plugins/cls/cli_plugin_cls.py
flight_profiler/plugins/console/__init__.py
flight_profiler/plugins/console/cli_plugin_console.py
flight_profiler/plugins/console/remote_interactive_console.py
flight_profiler/plugins/console/server_plugin_console.py
flight_profiler/plugins/getglobal/__init__.py
flight_profiler/plugins/getglobal/cli_plugin_getglobal.py
flight_profiler/plugins/getglobal/getglobal_agent.py
flight_profiler/plugins/getglobal/getglobal_parser.py
flight_profiler/plugins/getglobal/server_plugin_getglobal.py
flight_profiler/plugins/gilstat/__init__.py
flight_profiler/plugins/gilstat/cli_plugin_gilstat.py
flight_profiler/plugins/gilstat/gilstat_parser.py
flight_profiler/plugins/gilstat/server_plugin_gilstat.py
flight_profiler/plugins/help/__init__.py
flight_profiler/plugins/help/cli_plugin_help.py
flight_profiler/plugins/help/help_agent.py
flight_profiler/plugins/history/__init__.py
flight_profiler/plugins/history/cli_plugin_history.py
flight_profiler/plugins/history/history_parser.py
flight_profiler-1.0.2.dist-info/METADATA
flight_profiler-1.0.2.dist-info/WHEEL
flight_profiler-1.0.2.dist-info/entry_points.txt
flight_profiler-1.0.2.dist-info/licenses/LICENSE
flight_profiler-1.0.2.dist-info/licenses/NOTICE
flight_profiler-1.0.2.dist-info/RECORD
