Metadata-Version: 2.4
Name: flight_profiler
Version: 1.0.2
Summary: A diagnostic toolkit for on-the-fly analysis of remote python processes.
License-File: LICENSE
License-File: NOTICE
Requires-Python: >=3.8,<3.15
Classifier: Programming Language :: Python :: 3
Classifier: Programming Language :: Python :: 3.8
Classifier: Programming Language :: Python :: 3.9
Classifier: Programming Language :: Python :: 3.10
Classifier: Programming Language :: Python :: 3.11
Classifier: Programming Language :: Python :: 3.12
Classifier: Programming Language :: Python :: 3.13
Classifier: Programming Language :: Python :: 3.14
Requires-Dist: py-spy (>=0.4.0,<0.5.0) ; python_version in "3.8, 3.9, 3.10, 3.11, 3.12, 3.13"
Requires-Dist: pympler (>=1.1,<2.0)
Requires-Dist: pystack (>=1.4.1,<2.0.0) ; sys_platform == "linux"
Project-URL: Homepage, https://github.com/alibaba/PyFlightProfiler
